<?xml version="1.0" encoding="UTF-8"?>
<GenRun Id="impl_1" LaunchPart="xc7a35tcpg236-1" LaunchTime="1664301261">
  <File Type="ROUTE-PWR" Name="equationsModule_power_routed.rpt"/>
  <File Type="PA-TCL" Name="equationsModule.tcl"/>
  <File Type="ROUTE-PWR-SUM" Name="equationsModule_power_summary_routed.pb"/>
  <File Type="REPORTS-TCL" Name="equationsModule_reports.tcl"/>
  <File Type="BITSTR-MSK" Name="equationsModule.msk"/>
  <File Type="ROUTE-CLK" Name="equationsModule_clock_utilization_routed.rpt"/>
  <File Type="RDI-RDI" Name="equationsModule.vdi"/>
  <File Type="BG-BIT" Name="equationsModule.bit"/>
  <File Type="BG-DRC" Name="equationsModule.drc"/>
  <File Type="BG-BGN" Name="equationsModule.bgn"/>
  <File Type="BG-BIN" Name="equationsModule.bin"/>
  <File Type="BITSTR-RBT" Name="equationsModule.rbt"/>
  <File Type="BITSTR-NKY" Name="equationsModule.nky"/>
  <File Type="BITSTR-BMM" Name="equationsModule_bd.bmm"/>
  <File Type="BITSTR-MMI" Name="equationsModule.mmi"/>
  <File Type="ROUTE-METHODOLOGY-DRC" Name="equationsModule_methodology_drc_routed.rpt"/>
  <File Type="BITSTR-SYSDEF" Name="equationsModule.sysdef"/>
  <File Type="BITSTR-LTX" Name="debug_nets.ltx"/>
  <File Type="BITSTR-LTX" Name="equationsModule.ltx"/>
  <File Type="WBT-USG" Name="usage_statistics_webtalk.html"/>
  <File Type="OPT-DRC" Name="equationsModule_drc_opted.rpt"/>
  <File Type="OPT-HWDEF" Name="equationsModule.hwdef"/>
  <File Type="PLACE-IO" Name="equationsModule_io_placed.rpt"/>
  <File Type="PLACE-UTIL" Name="equationsModule_utilization_placed.rpt"/>
  <File Type="PLACE-UTIL-PB" Name="equationsModule_utilization_placed.pb"/>
  <File Type="PLACE-CTRL" Name="equationsModule_control_sets_placed.rpt"/>
  <File Type="PLACE-PRE-SIMILARITY" Name="equationsModule_incremental_reuse_pre_placed.rpt"/>
  <File Type="ROUTE-DRC" Name="equationsModule_drc_routed.rpt"/>
  <File Type="ROUTE-DRC-PB" Name="equationsModule_drc_routed.pb"/>
  <File Type="ROUTE-PWR-RPX" Name="equationsModule_power_routed.rpx"/>
  <File Type="ROUTE-STATUS" Name="equationsModule_route_status.rpt"/>
  <File Type="ROUTE-STATUS-PB" Name="equationsModule_route_status.pb"/>
  <File Type="ROUTE-DCP" Name="equationsModule_routed.dcp"/>
  <File Type="ROUTE-ERROR-DCP" Name="equationsModule_routed_error.dcp"/>
  <File Type="ROUTE-BLACKBOX-DCP" Name="equationsModule_routed_bb.dcp"/>
  <File Type="ROUTE-TIMINGSUMMARY" Name="equationsModule_timing_summary_routed.rpt"/>
  <File Type="ROUTE-TIMING-PB" Name="equationsModule_timing_summary_routed.pb"/>
  <File Type="ROUTE-TIMING-RPX" Name="equationsModule_timing_summary_routed.rpx"/>
  <File Type="ROUTE-BUS-SKEW" Name="equationsModule_bus_skew_routed.rpt"/>
  <File Type="ROUTE-BUS-SKEW-PB" Name="equationsModule_bus_skew_routed.pb"/>
  <File Type="ROUTE-BUS-SKEW-RPX" Name="equationsModule_bus_skew_routed.rpx"/>
  <File Type="OPT-DCP" Name="equationsModule_opt.dcp"/>
  <File Type="PLACE-DCP" Name="equationsModule_placed.dcp"/>
  <File Type="PWROPT-DCP" Name="equationsModule_pwropt.dcp"/>
  <File Type="POSTPLACE-PWROPT-DCP" Name="equationsModule_postplace_pwropt.dcp"/>
  <File Type="PHYSOPT-DCP" Name="equationsModule_physopt.dcp"/>
  <File Type="POSTROUTE-PHYSOPT-DCP" Name="equationsModule_postroute_physopt.dcp"/>
  <File Type="POSTROUTE-PHYSOPT-BLACKBOX-DCP" Name="equationsModule_postroute_physopt_bb.dcp"/>
  <File Type="ROUTE-METHODOLOGY-DRC-PB" Name="equationsModule_methodology_drc_routed.pb"/>
  <File Type="ROUTE-DRC-RPX" Name="equationsModule_drc_routed.rpx"/>
  <File Type="ROUTE-METHODOLOGY-DRC-RPX" Name="equationsModule_methodology_drc_routed.rpx"/>
  <File Type="PDI-FILE" Name="equationsModule.pdi"/>
  <File Type="RCFI_FILE" Name="equationsModule.rcfi"/>
  <File Type="CFI_FILE" Name="equationsModule.cfi"/>
  <File Type="RNPI_FILE" Name="equationsModule.rnpi"/>
  <File Type="NPI_FILE" Name="equationsModule.npi"/>
  <File Type="RBD_FILE" Name="equationsModule.rbd"/>
  <File Type="ROUTE-RQS" Name="equationsModule_routed.rqs"/>
  <File Type="POSTROUTE-PHYSOPT-RQS" Name="equationsModule_postroute_physopted.rqs"/>
  <File Type="ROUTE-RQS-RPT" Name="route_report_qor_suggestions_0.rpt"/>
  <File Type="POSTROUTE-PHYSOPT-RQS-RPT" Name="postroute_physopt_report_qor_suggestions_0.rpt"/>
  <FileSet Name="sources" Type="DesignSrcs" RelSrcDir="$PSRCDIR/sources_1" RelGenDir="$PGENDIR/sources_1">
    <Filter Type="Srcs"/>
    <File Path="$PSRCDIR/sources_1/new/equationsModule.sv">
      <FileInfo>
        <Attr Name="UsedIn" Val="synthesis"/>
        <Attr Name="UsedIn" Val="implementation"/>
        <Attr Name="UsedIn" Val="simulation"/>
      </FileInfo>
    </File>
    <Config>
      <Option Name="DesignMode" Val="RTL"/>
      <Option Name="TopModule" Val="equationsModule"/>
      <Option Name="TopAutoSet" Val="TRUE"/>
    </Config>
  </FileSet>
  <FileSet Name="constrs_in" Type="Constrs" RelSrcDir="$PSRCDIR/constrs_1">
    <Filter Type="Constrs"/>
    <Config>
      <Option Name="ConstrsType" Val="XDC"/>
    </Config>
  </FileSet>
  <FileSet Name="utils" Type="Utils" RelSrcDir="$PSRCDIR/utils_1">
    <Filter Type="Utils"/>
    <Config>
      <Option Name="TopAutoSet" Val="TRUE"/>
    </Config>
  </FileSet>
  <Strategy Version="1" Minor="2">
    <StratHandle Name="Vivado Implementation Defaults" Flow="Vivado Implementation 2022"/>
    <Step Id="init_design"/>
    <Step Id="opt_design"/>
    <Step Id="power_opt_design"/>
    <Step Id="place_design"/>
    <Step Id="post_place_power_opt_design"/>
    <Step Id="phys_opt_design"/>
    <Step Id="route_design"/>
    <Step Id="post_route_phys_opt_design"/>
    <Step Id="write_bitstream"/>
    <Step Id="write_device_image"/>
  </Strategy>
</GenRun>
